streamlit_xterm/__init__.py
streamlit_xterm/frontend/build/asset-manifest.json
streamlit_xterm/frontend/build/index.html
streamlit_xterm/frontend/build/xterm.css
streamlit_xterm/frontend/build/static/js/2.484077fd.chunk.js
streamlit_xterm/frontend/build/static/js/2.484077fd.chunk.js.LICENSE.txt
streamlit_xterm/frontend/build/static/js/2.484077fd.chunk.js.map
streamlit_xterm/frontend/build/static/js/main.eed2c2c0.chunk.js
streamlit_xterm/frontend/build/static/js/main.eed2c2c0.chunk.js.map
streamlit_xterm/frontend/build/static/js/runtime-main.624f085e.js
streamlit_xterm/frontend/build/static/js/runtime-main.624f085e.js.map
streamlit_xterm-0.0.4.dist-info/LICENSE
streamlit_xterm-0.0.4.dist-info/METADATA
streamlit_xterm-0.0.4.dist-info/WHEEL
streamlit_xterm-0.0.4.dist-info/top_level.txt
streamlit_xterm-0.0.4.dist-info/RECORD
