Metadata-Version: 2.1
Name: streamlit-xterm
Version: 0.0.4
Summary: streamlit component implementation of xterm.js
Home-page: 
Author: Connor Austin
Author-email: connoraustin22@gmail.com
Requires-Python: >=3.7
License-File: LICENSE
Requires-Dist: streamlit (>=0.63)
